{"name":"引论","slug":"引论","count":1,"postlist":[{"title":"操作系统-引论","uid":"39a1d68c8b246f2bec009a9ddf2e0be4","slug":"操作系统-引论","date":"2022-01-17T10:56:41.784Z","updated":"2020-10-05T12:46:21.914Z","comments":true,"path":"api/articles/操作系统-引论.json","keywords":null,"cover":[],"text":"一.操作系统引论1.操作系统的目标和功能目标 方便性 有效性 提高系统资源利用率 提高系统吞吐量 可扩充性 开放性 作用 OS作为用户与计算机硬件系统之间的接口 命令方式 系统调用方式 图标–窗口方式 OS实现了对计算机资源的抽象 2.操作系统的发展过程未配置操作系统的计算机系统...","link":"","photos":[],"count_time":{"symbolsCount":"1.8k","symbolsTime":"2 mins."},"categories":[{"name":"操作系统","slug":"操作系统","count":7,"path":"api/categories/操作系统.json"}],"tags":[{"name":"操作系统","slug":"操作系统","count":7,"path":"api/tags/操作系统.json"},{"name":"引论","slug":"引论","count":1,"path":"api/tags/引论.json"}],"author":{"name":"天琦","slug":"blog-author","avatar":"https://img-blog.csdnimg.cn/20210313122054101.png","link":"/","description":"为天地立心，为生民立命，为往圣继绝学，为万世开太平！！","socials":{"github":"","twitter":"","stackoverflow":"","wechat":"","qq":"","weibo":"","zhihu":"","csdn":"","juejin":"","customs":{}}}}]}